AUTHORS
CHANGELOG.md
LICENSE
MANIFEST.in
README.md
setup.cfg
setup.py
versioneer.py
src/libreflow/__init__.py
src/libreflow.andarta.egg-info/PKG-INFO
src/libreflow.andarta.egg-info/SOURCES.txt
src/libreflow.andarta.egg-info/dependency_links.txt
src/libreflow.andarta.egg-info/requires.txt
src/libreflow.andarta.egg-info/top_level.txt
src/libreflow/andarta/__init__.py
src/libreflow/andarta/_version.py
src/libreflow/andarta/gui.py
src/libreflow/andarta/custom_home/__init__.py
src/libreflow/andarta/custom_home/ui.py
src/libreflow/andarta/flow/__init__.py
src/libreflow/andarta/flow/asset.py
src/libreflow/andarta/flow/entity_manager.py
src/libreflow/andarta/flow/file.py
src/libreflow/andarta/flow/film.py
src/libreflow/andarta/flow/mytasks.py
src/libreflow/andarta/flow/shot.py
src/libreflow/andarta/flow/task.py
src/libreflow/andarta/flow/user.py
src/libreflow/andarta/flow/ui/__init__.py
src/libreflow/andarta/flow/ui/importfiles/__init__.py
src/libreflow/andarta/flow/ui/importfiles/custom_widget.py
src/libreflow/andarta/flow/ui/importfiles/files_list.py
src/libreflow/andarta/flow/ui/importfiles/target_wizard.py
src/libreflow/andarta/flow/ui/mytasks/__init__.py
src/libreflow/andarta/flow/ui/mytasks/mytasks.py
src/libreflow/andarta/resources/__init__.py
src/libreflow/andarta/resources/file_templates/__init__.py
src/libreflow/andarta/resources/file_templates/template.blend
src/libreflow/andarta/resources/file_templates/template.wav
src/libreflow/andarta/resources/gui/__init__.py
src/libreflow/andarta/resources/gui/styles/__init__.py
src/libreflow/andarta/resources/gui/styles/default_style/__init__.py
src/libreflow/andarta/resources/gui/styles/default_style/default_style.css
src/libreflow/andarta/utils/__init__.py
src/libreflow/andarta/utils/flow/__init__.py
src/libreflow/andarta/utils/flow/import_files.py