Metadata-Version: 2.1
Name: libreflow.andarta
Version: 2.3.0
Summary: Tailor-made flow for Andarta Pictures productions
Home-page: https://gitlab.com/lfs.coop/libreflow/libreflow.andarta
Author: Baptiste Delos, Flavio Perez, Valentin Braem
Author-email: baptiste@les-fees-speciales.coop, flavio@lfs.coop, valentinbraem1@gmail.com
License: LGPLv3+
Keywords: kabaret cgwire kitsu gazu animation pipeline libreflow
Classifier: Programming Language :: Python :: 3
Classifier: Intended Audience :: Developers
Classifier: Intended Audience :: End Users/Desktop
Classifier: Intended Audience :: Information Technology
Classifier: License :: OSI Approved :: GNU Lesser General Public License v3 or later (LGPLv3+)
Classifier: Operating System :: OS Independent
Requires-Python: >=3.8
License-File: LICENSE
License-File: AUTHORS
Requires-Dist: libreflow>=2.4.0
Requires-Dist: kabaret.flow_extensions>=1.0.0
